{
    "@class": "com.kony.gen.viz.model.component.KVizButton",
    "DNDConfig": null,
    "_bottom_": {
        "type": "string",
        "value": "5dp"
    },
    "_left_": {
        "type": "string",
        "value": "5dp"
    },
    "_margin_": [
        6,
        6,
        6,
        6
    ],
    "_padding_": [
        0,
        0,
        0,
        0
    ],
    "_right_": {
        "type": "string",
        "value": "10dp"
    },
    "_skin_": "s4fdd45d7372452d8f18eace6c7e866f",
    "_text_": "Next",
    "_top_": {
        "type": "string",
        "value": "5dp"
    },
    "canUpdateUI": true,
    "containerweight": 100,
    "contentalignment": 5,
    "displaytext": true,
    "focusskin": "s0fb9562105140c3b64f09729b2cea7c",
    "id": "ButtonBorderTripleRight",
    "ide_onClick": "AS_Button_j053228f4360433bb6471bfa678d5660",
    "ide_onTouchStart": "AS_Button_c4c1a0bdbde44095a352e8c4366d599f",
    "info": null,
    "isvisible": true,
    "kuid": "j1bf61d08928427aae3f8e90636cebb3",
    "name": "kony.ui.Button",
    "parent": "ContainerButtonBorderTripleRight",
    "pf": "frmRegisterUser",
    "wType": "Button",
    "zindex": 1
}