{
    "DNDConfig": null,
    "_height_": {
        "type": "string",
        "value": "55dp"
    },
    "_left_": {
        "type": "string",
        "value": "0dp"
    },
    "_margin_": [
        0,
        0,
        0,
        0
    ],
    "_orientation_": 6,
    "_padding_": [
        0,
        0,
        0,
        0
    ],
    "_percent_": true,
    "_skin_": "s689e70956c14513a208f78ec1abb8bb",
    "_top_": {
        "type": "string",
        "value": "425dp"
    },
    "_width_": {
        "type": "string",
        "value": "100%"
    },
    "allboxes": [],
    "autogrowmode": 0,
    "canUpdateUI": true,
    "children": [
        "lblOwnership",
        "lblOwnershipValue"
    ],
    "clipbounds": true,
    "containerweight": 100,
    "enablescrolling": true,
    "id": "flxOwnership",
    "info": null,
    "isvisible": true,
    "kuid": "fb4c9cd1835a4c6a90ea787c6b345b3b",
    "layouttype": 2,
    "masterType": 1,
    "name": "kony.ui.FlexContainer",
    "parent": "flxAccountDetails",
    "pf": "frmAccept",
    "snapgridsize": 10,
    "snaptogrid": true,
    "wType": "FlexContainer",
    "widgetalignment": 1,
    "zindex": 1
}